{
  "schema_version": "1.0.0",
  "case_id": "dyspnea-001",
  "case_number_in_pdf": 104,
  "topic": {
    "topic_start_page": 239,
    "topic_id": "dyspnea",
    "topic_label": "호흡곤란",
    "system": "호흡기"
  },
  "source": {
    "document": "CPX 증례.pdf",
    "document_page_range": {
      "start": 239,
      "end": 260
    },
    "extraction_method": "embedded_text_layer",
    "ocr_note": "OCR/embedded-text extraction was retained as-is; visually validate any high-stakes field before production use."
  },
  "patient_visible": {
    "identity": {
      "name": "강민경",
      "age": 52,
      "sex": "여자"
    },
    "setting": "응급실",
    "opening_statement": "숨이 차요",
    "vital_signs_available_on_scenario_card": {
      "blood_pressure": "125/80mmHg",
      "pulse": "100회/분",
      "respiratory_rate": null,
      "temperature": "36.5°C"
    },
    "opening_profile_text": "성별/나이\n여성/ 52세\n\"숨이 차요”",
    "history_blocks": {
      "onset": "오전 6시(현재 오전 10시)",
      "duration": "지속",
      "course": "비슷함",
      "experience": "처음",
      "character": "집안일 하기도 어려울 정도 말하는 것도 힘들어 보임, 화장실 가는 정도만 걸어도 숨\n이 참，가만히 있어도 숨이 참, 이전에는 계단을 올라도 숨이 차지 않았음",
      "associated_symptoms": "[전신] 발열/피로/체중 변화/부종(-/-/-/+，왼쪽 발목)\n[호홉] 흉통(+, 초반에 동반, 지속 시간 모름, 아프진 않고 답답한 느낌, NRS 3점)\n기침/가래/쌕쌕거림 ( - / - / - )\n[정신] 죽을것 같은 공포감(ᅳ). 불안( ± ,큰병일까봐)",
      "factors": "운동 시 악화, 누우면 악화, 호흡 중등도 grade 4\n자세 상관 X, 찬 바람을 맞아본 적 없어서 악화되는지 잘 모르겠음",
      "trauma_history": "일주일 전 발목 골절되어 누워 지냄, 수술하거나 입원하지는 않음",
      "past_history": "관절염",
      "medications": "관절영양제(먹다 안 먹다 한다고 강조함)",
      "social_history": "흡연(一), 음주(+, social)\n운동 ：\n관절 때문에 살 빼려고 운동 시작했으나 빗길에 넘어져 발목을 다친 뒤로 운동\n을 못하고 있음",
      "gynecologic_history": "폐경, 자녀 2명 자연분만\nGeneral\nV/S : 맥박 : 100회/분, 호흡 : 23회/분\nHEENT\n눈/구강(一/ - ), 갑상샘/ 림프절(ᅳ/-), 피부 긴장도/부종(ᅳ/一)"
    },
    "physical_exam_results": "Chest\n흉부 ：\n시/촉/타/청 (- / - / - / _ > . 심음 (_)\nExtermity\n곤봉지/청색증(-/-> , Homan’s sign : 하려했으나 반대편은 할 수\n있지만. 아픈 부위를 시도하면 부목 푼지 얼마되지 않았고, 아파서\n못하겠다고 거절, 왼쪽 발목에 멍 분장되어 있음, 실기 보는 날짜에\n따라 Homan’s sign 시행 가능 여부 다름(왼쪽 +, 오른쪽- )\n|oh\nm\nM",
    "patient_question_or_concern": "I 이사항\n“갑자기 이렇게 심해서 큰 병은 아닐까 걱정돼요，아까 말씀하신 검사 결과는 언제 알 수\n있나요?二\n말이 느리고, 발목에 분장되어 있음\n실전\n모의\n증례 i\n' 54세 남자 임동재씨가 숨이 차서 응급실로 내원하였다.\n[활력 징후] 혈압 : 127/77mmHg\n맥박 : 85회/분\n상황\n호흡: 19희/분\n지침\n체온 ：\n36.5°C\n[응人I자는 이 환자에게] 증상과 관련된 병력을 청취하고\n증상과 관련된 적절한 신체 진찰을 시행한 후,\n추정 진단과 향후 진단 계획 등에 대해 환자와 논의하시오■\n환자\n교육\n가능성이 높은 진단 2개\n1. COPD\n2. 진폐증\n필요한 검사 계획 3가지\n1. 폐7 ᅵ능검사\n2. 흉부영상검사\n3. ABGA\n필요한 치료 계획 3가지\n1• 생활 습관 교육(e.g. 금연)\n2. 7 1관지확장제(LAM/V LABA)\n3. 응급 상황 교육\n환자가 호흡곤란증상으로 내원하면 그 원인이 호흡기인지 심혈관^인\n지 아니면 그 외의 원인인지 감별하는 것이 중요합니다. 호흡기에 의한\n호흡곤란의 경우환기장애, 가스교환장애, 호흡조절이상등이 원인이 될 수 있습니다. 본 증례의\n환자는 중년의 남자로 현재는금연 중이지만，과거 50갑년의 흡연자로 만성 폐쇄성폐질환{COPD)\n에 의한환기장애로 인한호흡곤•란이 가장의심됩니다. 환자는URIHx•가 있는데, COPD의 경우\nURI에 의한급성 악화가가능하기 때문에 만성 폐쇄성폐질환을 더욱 의심할수 있습니다. 그러나\n환자의 근무 환경 상 먼지가 많기 때문에 직업성 폐질환 역시 감별할 필요가 있습니다.\nCOPD의 경우 폐기능검사를통해 obstructive pattern 확인 및 BDRresponse로 기도의 비가역성\n을 확인하면 진단할 수 있습니다. 또한, CXR, HRCT 등을 통해 폐의 병 변을 확인할 수 있는데, 특히\n본증례의 환자는건강검진 상폐기종이 있으므로 CT •등어!서 해당 병변을관찰할수 있습니다.\n성별/나이\n남성/ 54세\n주소\n“숨이 차요(환자가 침대에 앉아 있음)”\n0\n6개월 전\nL\n\nD\n지속\nCo\n과거에 감기 걸렸을 때 기침, 가래 심하고 숨이 찼는데, 그때 감기에서 회복하고 괜찮\n았다가 6개월 전부터 호흡곤란 다시 생김\nEx\n감기 걸린 뒤로 호흡곤란 증상 다시 생긴 것 같음\nC\n가만히 있을 때는 괜찮음，옷 갈아입을 때는 괜찮음, 일하거나 계단 오를 때 숨 차는\n증상 심함，평지 걸어도 동년배에 비해 뒤처짐(-)\n무거운 것 들 때(+)\nA\n[전신] 발열/오한/피로/체중 변화/부종( - / - / - / - / - )\n[호흡] 흉통/두근거림/인후통/쌕쌕거림(ᅵ/■/+，6개월 전 감기 때/ - )\n기침/가래/콧물(ᅳ/+, 흰색，아침에 회색으로 나오고 시간 지나면 맑아짐，\n하루 양 합치면 티스푼 1 개 정도/一), “가래 억지로 뱉으려고 기침 많이 함”\n[정신] 죽을것 같은공포감(一),불안(ᅵ)\n입술 부종/두드러기( - / - )\nF\n운동 및 움직이면 악화, 쉬면 완화\nE\n8년 전, 4년 전 둘 다 폐기종(+), \"폐가 커져 있다고 들었어요”\n독감. 폐렴구균 예방접종은 맞았다고 말함\n외\n\n과\n\n약\n\n人卜\n음주( - ) ，흡연(+, 2PX25Y+10년 전 끊음)\n직업 : 정육식당 운영 ( 먼지는 없는데 연기가 많음)，일할 때 호흡곤란 더 심해짐 (+)\n가\n\nP/E\nGeneral\nV/S ：\nstable\nHEENT\n눈/구강(一/ - ), 갑상샘/ 림프절(-/-> ，피부 긴장도/부종( - / - )\nChest\n흉부 시/촉/ 타/청( - / - / - / - ) , 심음(-)\nExtermity\n곤봉지/청색증(一/ᅳ)\n질문",
    "actor_notes_or_special_behavior": "w m i 실전모의증례\n43세 남자 신정호씨가 숨이 차 내원하였다.\n^•황\n지침\n[활력 징후] 혈압 : 114/70mrmHg\n맥박 : 80회/분\n호흡 : 18회/분\n체온 : 37.213\n[응시자는 이 환자에게]\n증상과 관련된 병력을 청취하고\n증상과 관련된 적절한 신체 진찰을 시행한 후,\n추정 진단과 향후 진단 계획 등에 대해 환자와 논의하시오\n가능성이 높은 진단 3개\n1. 만성 폐쇄성폐질환\n2. 간질성 폐질환\n3. 폐암\n필요한 검사 계획 3가지\n교육\n1. 폐7 ᅵ능검사\n2. 흉부 X-ray\n3. 흉부 CT\n필요한 치료 계획 2가지\n1. 기관지확장제\n2. 금연\n환자는 2년 전부터 호흡곤란을 호소하고 있었으며, 흡연력도 25갑년\n으로 가래, 쌕쌕거림으로 만성 폐쇄성폐질환이 가장 의심되는 상황입\n니다• 평소 약물 사용이 중요함을 교육하고, 급성 악화 시 처치 방법에 대해서 반드시 교육하여\n야합니다.\n호흡곤란으로 불안을 호소하거나 숨이 차 대답하는데 어려음이 있을 수 있으니, 이를 배려하여\n문진하는 것이 좋겠습니다. 만성 폐쇄성폐질환 환자는 호흡기 질환 고위험군으로 예방접종 여\n부도 확인하고 교육 시에 고려해야 합니다.\n\n성별/나이\n남성/ 43세\n주소\n“숨이 차요”\n0\n3개월 전\nL\n\nD\n\nCo\n3개월 전부터 더 심해짐\nEx\n2년 전부터\nC\n2년 전에는 계단 오를 때 힘듬. 최근엔 평지 걸어도 숨 참\n평범한 일상 생활이나 휴식 시에는 괜찮음\nA\n[전신]\n발열/식은땀/체중감소/오한/피로감 ( - / - / _ / - / - )\n[호홉기/ 순환기]\n기침/콧물/ 가래/두근거림\n(- / - / + , 1 달 전부터. 노란색이었다가 요즘 흰색으로 바뀜/一)\n쌕쌕거림(+), 가슴 통증/야간 발한/객혈/흉통(- / - / - / 니\n[내분비]\n더위불내성(ᅳ)\n[정신]\n불안/죽을 것 같은 느낌(一/ᅳ)\nF\n악화 : 운동 시(+), 누운 자세/찬 공기/일중 변화/계절 변화( - / - / - / - )\n완화 : 휴식 (+>\nE\n1 년 전 건강 검진 상 이상 없음, 당시 흉부 X-ray 찍음\n외\n최근 오래 누워 있었던 적(ᅳ)\n과\n1 년 전 심한 감기, 천식/결핵/아토피 피부염/알러지 비염(一/ - / - / ᅳ)\n약\n\n人^\n술(+. social), 담배(+, 25갑년. 하루 1갑)\n직업 : 택배 기사(먼지 많지 않음)/운동(ᅳ)\n가\n\nP/E\nGeneral\nV/S 확인\nHEENT\n결막/공막( - / - ) , 입/피부 탈수 소견(一/ - ), 림프절(-)\nChest\n흉부 시/촉/타/청( - / - / - / - ) . 심장 청진(-)\nExtermity\n피부 긴장도，오목 부종 정상. 곤봉지(- )\n질문\n“택배 일에 지장이 갈까 걱정이에요.”\n특이 사항\n대답이 느려서 시간이 부족할 수 있음\nn { 실전\n모의\n증례\n34세 남자 박현우씨가 숨 쉬는 게 힘들어 내원하였다.\n지침\n[활력 징후] 혈압 : 110/82mmHg\n맥박 : 74회/분\n^흡 : 23회/분\n체온 ：\n37.2°C\n[응시자는 이 환자에게] 증상과 관련된 병력을 청취하고\n증상과 관련된 적절한 신체 진찰을 시행한 후,\n추정 진단과 향후 진단 계획 등에 대해 환자와 논의하시오■\n가능성이 높은 진단 3개\n1. 급성 심부전\n2. 급성 바이러스 폐렴\n3. 심장막염\n환자\n필요한 검사 계획 3가지\n1. 심초음파\n2. 흉부 X-ray\n3. 혈액검人卜\n필요한 치료 계획 1 가지\n1. 익물 치료\n호소하는 증상이 애매하여 확실히 진단이 좁혀지지 않는 증례입니다.\n처음 CPX를 시작할 때는 추정 진단에 대해서 확신이 없으면 환자에게\n말을 꺼낼 때 조심스러워하는 경향이 있습니다. 내가 생각한 것이 맞을까 걱정하는 것이지요.\nCPX에서 중요한 것은 실제적 인 답이 아니라, 얼마나 논리적으로 추정 진단을 잡았고 그를 자신\n있게 말할 수 있냐는 것입니다. 병력 청취만으로 추정 진단이 확실하게 좁혀지지 않더라도 자신\n있계 추정 진단과그에 따른 검사를 설명할 수 있도록 연습하세요.\n현재 환자의 경우 심부전이 가장 의심되고, 단서가 조금부족하긴 하나 최근 감염으로 인해 심\n근에 감염이 생기고, 그로 인해 심부전이 생기지 않았을까추정해 볼 수 있습니다.\n성별/나이\n남성/ 34세\n“숨 쉬는 게 힘들어요”\n0\n3일 전\nL\n\nD\n3일 내내 지속됨\nCo\n심해짐\nEx\n\nC\n평소에도 계단 올라갈 때 숨이 참, 3일 전부터 평지 걸어도 숨 참\n휴식할 때 괜찮음\nA\n[전신] 발열(+, 최근 감기 걸렸을 때 발열), 식은땀/체중 감소/오한(一/ᅳ/ᅳ)\n피로감(+), 최근 감기(+, 일주일 전)\n[호흡기/순환기]\n기침/콧물/가래/두근거림 (+, 누울 때 악화/ - / 一/ᅳ)\n쌕쌕거림/가슴 통증/야간 발한/객혈/흉통(一/一/一/ - / - )\n부종(+, 얼굴)\n[내분비]\n더위불내성(一)\n[정신]\n불안卜),죽을것 같은 느낌(ᅳ)\nF\n악화 : 움직일 때(+), 누운 자세(+)\nE\n건강 검진에서 이상 없음\n외\n최근 오래 누워 있었던 적(ᅳ)\n과\n고지혈증(+, 치료 받지 않음), 천식(+, 어렸을 때)\n결핵/아토피 피부염/알러지 비염(ᅳ/ - / - )\n약\n감기약(+, 최근 감기로 4일 전 복용, 현재 중단)\n人^\n술(+. 일주일에 1 〜2번, 하루에 소주 3잔), 담배(+, 17갑년，하루 1 갑)\n직업 : 마트 배송 업무( 먼지 많지 않음)\n가\n\nP/E\nGeneral\nV/S 확인\nHEENT\n결막/공막(-/ -), 입/피부 탈수 소견(-/->, 림프절/목정맥 확장(- / - )\nChest\n흉부 시/촉/타/청(ᅳ/_/-/_> , 심장 청진(ᅳ)\nExtermity\n피부 긴장도* 오목 부종 정상, 곤봉지(-)\nId*\nn|oi<\n신\n:\n질문\nB\n[ 실전\n모의\n증례\n26세 여자 신지은씨가 숨이 차 힘들어 내원하였다.\n^■황\n지침\n[활력 징후] 혈압 : 114/78mmHg\n맥박 : 80회/분\n호흡 : 17회/분\n체온 : 37.5°C\n[응人I자는 이 환자에게]\n증상과 관련된 병력을 청취하고\n증상과 관련된 적절한 신체 진찰을 시행한 후,\n추정 진단과 향후 진단 계획 등에 대해 환자와 논의하시오\n가능성이 높은 진단 2개\n1. 결핵\n2. 기흉\n필요한 검사 계획 3가지\n교육\n1. 흉부 X-ray\n2. 객담항산균검사\n3. 흉부 CT\n필요한 치료 계획 1 가지\n1. 항결핵제\n호흡곤란은 다양한 계통의 문제로 생길 수 있습니다.\n콜\n'\n이 환자의 경우 명확히 결핵이라고 진단 내릴 순 없지만 어머니의 결\n핵 과거력, 야간 발한，기침 등으로 결핵이 가장 의심되는상황입니다.\n결핵의 경우 꾸준한 치료가 중요함을 설명하고, 동거인도 같이 검사를 받아야 된다는 점, 일정\n기간 격리가 필요함을 설명해야겠지요.\n성별/나이\n여성/ 26세\n“가슴이 답답해요”\n0\n1주전\nL\n\nD\n\nCo\n\nEx\n\nC\n운동, 계단 오를 때 숨 참，휴식 시나 평지 걸을 때는 괜찮다.\nA\n[전신]\n발열/식은땀/체중 감소/오한/피로감/최근 감기\n(+，최근에 밤에 열이 조금 나는 것 같기도 함/ - / - / + /+ /-)\n[호흡기/ 순환기]\n기침/콧물/가래/두근거림 (+/ᅳ/一/ - )\n쌕쌕거림/가슴 통증/야간 발한/객혈/부종( - / _ / + / - / _ )\n오른쪽 등 뻐근한 느낌, 가슴 답답함(+, 1달 전부터)\n[내분비]\n더위불내성(一)\n[정신]\n불안/죽을 것 같은 느낌(ᅳ/ᅳ)\nF\n악화 : 움직일 때(+), 완화 : 휴식(+)\n숨쉴 때 가슴통증심해짐\nE\n\n외\n최근 오래 누워 있었던 적(ᅳ)\n과\n천식/결핵/아토피 피부염/알러지 비염( - / - / - / - )\n약\n\n사\n술/담배(一/一), 직업 : 운동 관련 자격증 준비 중\n가\n1\n어머니 : 결핵(20년 전)，부모님과 함께 거주 중/동생 ：\n알레르기성 천식\n여\n규칙적\nP/E\nGeneral\nV/S 확인\nHEENT\n결막/공막(一/ - )，입/피부 탈수 소견(- / - ), 림프절/목정맥 확장(一/-)\nChest\n흉부 시/촉/ 타/청( - / - / - / 一), 심장 청진(-)\nExtermity\n피부 긴장도，오목 부종 정상. 곤봉지(- )\n질문\n“치료 중에는 운동해도 되나요? ”\n특이職\n\nS\n느\n■\n실전\n모의\n증례\n58세 여자 황윤정씨가 숨이 차서 내원하였다.\n[활력 징후] 혈압 : 120/80mmHg\n맥박 : 80회/분\n호音 : 16호|/분\n지침\n체온 ：\n36.81C\n|轉義|옳馨\n[응시자는 이 환자에게] 증상과 관련된 병력을 청취하고\n증상과 관련된 적절한 신체 진찰을 시행한 후.\n추정 진단과 향후 진단 계획 등에 대해 환자와 논의하시오\nV스f 시 震■'重• 가능성이 높은 진단 3개\n환자\n1. COPD\n2. IPF\n3. 심부전\n교육\n필요한 검사 계획 3가지\n1. 흉부 X-ray\n2. 폐71능검사\n3. 흉부 CT\n호흡곤란은 갑자기 발생한 것인지 꾸준히 악화된 것인지를 구분하는\n것이 먼저 해야할 일입니다. 갑자기 발생한 것이라면 응급상황일 수\n있으므로 빠르게 처치하고, 검사와 치료를 속히 진행해야합니다.\n이 케이스의 경우 만성적인 호흡곤란이므로 COPD, IPF, 천식, 심부전 둥을 염두해 두고 접근하\n는 것이 적절합니다.\n진폐증의 경우 직업력이 중요하므로 어떠한 일을 하는지 확인하는 것도 중요합니다.\n성별/나이\n여성/ 58세\n^소\n“일할 때 숨 차요”\n0\n3개월 전\nL\n\nD\n\nCo\n심해짐\nEx\n3년 전. 계단오를 때 숨참\nC\n흰색 가래 동반, 객혈(-)\nA\n[전신]\n발열/식은땀/체중감소/오한/피로감 ( - / - / - / - / - )\n[호흡기/ 순환기]\n호흡곤란/흉통/어지럼/두근거림 (+/- / 一/ - )\n기침/가래/쌕색거림 (+/+/+)\n[정신]\n우울/불안 (-/->\nF\n악화 : 운동할 때\n완화 : 휴식/자세에 따른 변화 없음\nE\n외\n과\nDM/TB/HTN/간염 ( - / - / - / - )\n약\n\n사\n술(+, social), 담배(+, 25갑년)\n직업 ：\n인테리어 업자，Stress(-)\n가\n여\n폐경\nP/E\nGeneral\nV/S 확인\nHEENT\n구강 탈수 소견(ᅳ), 갑상샘(ᅳ)\nChest\n흉부 시/청/타/촉 정상, 심음(-)\nExtermity\n피부 긴장도/오목 부종( - / - )\n곤봉지 (-)\n질문\n특이 사항\n대답이 느려서 시간이 부족할 수 있음\na { 실전\n모의\n증례\n65세 여자 김지민씨가 숨쉬기가 힘들어 내원하였다.\n지침\n馨나 ■\nV.；\n\n[활력 징휘 혈압 : 130/85mmHg\n맥박 ：\n102회/분\n■2■音 : 28회/분\n체온 : 36.6°C\n[응시자는 이 환자에게] 증상과 관련된 병력을 청취하고\n증상과 관련된 적절한 신체 진찰을 시행한 후,\n추정 진단과 향후 진단 계획 등에 대해 환자와 논의하시오\n가능성이 높은 진단 2개\n환자\n1.PTE\n2. DVT\n교육\n필요한 검사 계획 3가지\n1. ABGA\n2. Chest CT\n3. 다리정맥초음파\n예상\n1. 설명동의서 받기 : 흉부 조영 CT 검사가 필요한 환자이므로 검사에 대해 설명하\n고 동의서를 받습니다.\n술기\n2. 환자 상태 보고 ：\n응급실에 내원한 환자의 시나리오로 교수님께 환자 상태 보고를\n시행할 수 있습니다.\ny ^ x\n호흡곤란의 원인을 호흡기, 순환기，내분비, 정신으로 나누어 잘 정리\n해두도록합니다.\n갑자기 호흡곤란이 심해지는 경우 응급 상황일 수 있으므로 바로 병원으로 오도록 잘 교육하고>\n원인을 감별하기 위해서 위 케이스 경우 이전 수술/외상 여부를 꼭 확인하도록 합니다.\n원인을 감별하기 위해서 호흡 양상，흡연력, 악화 요인 등을 잘물어 보도록 합니다.\n성별/나이\n여성/ 65세\n주소\n“숨쉬기가 너무 힘들어요”\n0\n2시간 전\nL\n가슴전체\nD\n계속\nCo\n처음과 비슷\nEx\nC\n가슴 전체의 답답함과 뻐근함 호소\nA\n[전신]\n발열/오한/식은땀/체중 감소( - / - / - / - )\n[호흡기/순환기]\n호흡곤란/흉통 (+ /-)\nF\n악화 (+) : 누울 때\nE\n\n외\n다리 골절 (+) : 2주간 누워 있음\n과\nD M /T B /H T N /간염 ( - / - / + / - )\n약\nAmlodipine(혈압 잘 조절됨), 폐경 치료(-)\n사\n술/담배/커피 ( - / - / - )\n가\n언니 : 고혈압, 아버지 : 심근경색으로 人방\n여\n폐경\nGeneral\nV /S 확인\nHEENT\n입/피부 탈수 소견( - / - ) , 결막/공막( - / - )\nP/E\nChest\n\nAbdomen\n\nExtermity\nRt. Homan sign(+)\nQ|0I>\nvj\n질문\n특이 ^卜항\n신체 진찰하는 침대에 앉아 있음\na { 실전\n모의\n증례\n70세 남자 박진영씨가 숨이 차서 내원하였다.\n[활력 징후] 혈압 : 120/80mmHg\n맥박 : 90회/분\n^■황\n오읍 - 18회/분\n지침\n체온 ：\n36.6°C\n[응시자는 이 환자에게] 증상과 관련된 병력을 청취하고\n증상과 관련된 적절한 신체 진찰을 시행한 후,\n추정 진단과 향후 진단 계획 등에 대해 환자와 논의하시오.\n삶’\n가능성이 높은 진단 3개\n환자\n1. COPD\n2. 천식\n3. 특발성 폐섬유화증\n7■교육\n필요한 검사 계획 3가지\n1. 폐고 I능검人F\n2. 단순 흉부 방사선 촬영\n3. 흉부 CT\n호흡곤란의 원인을 호흡기，순환기, 내분비, 정신으로 나누어 잘 정리\n해 두도록 합니다. 갑자기 호흡곤란이 심해지는 경우응급 상황일 수\n있으므로 바로 병원으로 오도록 잘 교육하고，원인을 감별하기 위해서 호흡 양상, 홉연력, 악화 요\n인 등을 잘 물어 보도록 합니 다.\n위의 케이스 경우금연과 독감 예방접종의 중요성에 대해서 잘 설명하도록 합니다.\nᅵ\n‘ᅵ\n」—■\n^ —\n성별/나이\n남성/ 70세\n“숨쉬기가 너무 힘들어요”\n0\n1년전\nL\n\nD\n^卜루 종일\nCo\n심해짐\nEx\n\nC\n들이쉴 때, 내쉴 때 차이 없음\nA\n[전신] 발열/오한/부종/체중 변화( - / ᅳ/ - / - )\n[호흡기/ 순환기] 기침/콧물/가래/두근거림(ᅳ/ᅳ/ᅳ/ᅳ), 쌕쌕거림(+)\n[소화기] 설사/구토( - / - )\n[내분비] 더위불내성 (-)\nF\n악화 (+) ：\n운동 후, 일상 생활 지장은 심하지 않음\nE\n\n외\n과\nDM/TB/HTN/간염 (- / - / + / - )\n약\n혈압약 (+)\n사\n술(-, 끊은 지 20년)，담배(+. 50갑년), 커피 (-)\n가\n어머니 : 고혈압\nGeneral\nV/S 확인\nP/E\nHEENT\n입/피부 탈수 소견( - / 一)，결막/공막(ᅳ/ - )\n경동맥/경정맥 정상\n■샘 정상\nChest\n심음 정상\n숨 크게 들이쉬지 못함\nAbdomen\n\nExtermity\n\n질문\n특이\n항\n\nEM\n실전모의증례\n\n47세 남자 김재환씨가 숨을 쉬기 어렵다며 내원하였다.\n[활력 징후] 혈압 : 124/68mmHg\n맥박 : 90회/분\n^■황\n호흡 : 18회/분\n지침\n체온 ：\n36.4°C\n[응시자는 이 환자에게] 증상과 관련된 병력을 청취하고\n증상과 관련된 적절한 신체 진찰을 시행한 후,\n추정 진단과 향후 진단 계획 등에 대해 환자와 논의하시오.\n가능성이 높은 진단 3개\n1. 진폐증\n2. COPD\n3. 폐결핵\n필요한 검사 계획 2가지\n1.CXR\n2.ABGA\n댜\n호흡곤란은 응급일 수 있는케이스입니다. 따라서 진료 시작 전, 진료\n받기 너무 힘드制는 않은지 여쯤고，진료 도중에라도 언제든 힘드시\n면 말씀해 달라고 한 뒤 진료를 시작하시 면 좋습니다.\n건강 검진 꼭 여줘보시고, 직업력의 경우에는 가끔 탄광일 하시거나 먼지 많은곳에서 일한 적\n없으신 지 콕 찝어서 여줘봐야 상세히 알려주시는 경우도 있습니다.\n흉부 신체 진찰 때에는 꼭 환자분께 상의를 위로 을려도 되는지 여줍고> ‘맨살’ 위에 진찰하셔야\n하는 것 잊지 않으셔야 합니다.\n실제로 연습 때 항상 옷 위로 진찰하다가 시험장에서도 똑같이 옷 위로 P/E한 분들 꽤 있었다는\n사실을 기억하기 바랍니다.\n성별/나이\n남성/ 47세\n.\n.\n“숨이 차요”\n0\n3달 전\nL\n\nD\n지속적\nCo\n비슷함\nEx\n처음\nC\n주로 운동하거나 계단 오를 때 숨차고 휴식 시 완화\nA\n[전신] 발열(- )，체중 변화( - )，실신(-)\n[호흡기] 기침(+, 6달 전부터), 가래(-), 흉통(一). 쌕쌕거림(一)\n[출혈 경향] 양치할 때 피가 잘 나는지(ᅳ)\n[정신] 스트레스(- ), 불안( - ) ,공황장애(-)\n[기타] 다리 부종/압통/발적(一/一/ - )\nF\n[악화] 계단 오를때,운동할때\n[완화] 휴식/자세，계절, 시간,장소에는 무관함\nE\n5년 전 건강 검진 : CXR 상 뿌연 폐\n외\n과\nDM/HTN/dyslipidemia/TB/^g(-/-/-/+/-) ：\n대학생 때 결핵 앓은 후 완치\n약\n卜특이사항^음\n人^\n술 : 가끔，담배 : 5년 전 끊음(과거 35갑년)\n직업 : 현재 철물점(5년), 과거 탄광(15년), 공人f장(15년) 일했음\n가\n어머니 : 폐렴，아버지 : 고혈압\nGeneral\n활력 징후 확인 ：\n혈압, 맥박수. 호흡수 확인 후 응급 상황 배제\nP/E\nHEENT\n눈(결막) 시진 경정맥 시진, 경동맥 청진, 경부 갑상샘. 림프절 촉진\n정상\nChest\n흉부 시/촉/타/청, 심장 청진 모두 정상\nAbdomen\n\nExtermity\n곤봉지, 청색증 모두 정상\n질문\n\n특이 人땅\n\n1^\n실전\n모의\n증례\n지침\n55세 남자 이규범씨가 숨을 쉬기 어렵다며 내원하였다.\n[활력 징후] 혈압 : 120/80mmHg\n맥박 ：\n81회/분\n호흡 : 21회/분\n체온 ：\n36.8°C\n[응시자는 이 환자에게] 증상과 관련된 병력을 청취하고\n증상과 관련된 적절한 신체 진찰을 시행한 후.\n추정 진단과 향후 진단 계획 등에 대해 환자와 논의하시오\n환자\n교육\n가능성이 높은 진단 3개\n1. 천식\n1. 알레르기 비염\n3. 기관지 천식\n필요한 검사 계획 3가지\n1. 폐7 1능검사\n2. 피부따끔검사\n3. 7 1관지내시경\n계절에 호흡곤란이 심해지는 환자입니다. 또한 운동 시에도 심해지고\n이전에도 비슷한 경험이 있던 환자입니다. 신체 진찰에서 이상 소견이\n없었던 점을 모두 고려했을 때 천식이 가장 의심됩니다. 하지만 그 외에도 호흡곤란에는 여러\n원인이 있기 때문에 의심가는 질환만 물어 볼 것이 아니라 다양한 원인 감별을 위한 질문을 해\n야할 것입니다.\n천식같은 경•우는 교육이 중요하기 때문에 교육도 꼼꼼히 해야 할 것입니다.\n\n^\n성별/나이\n남성/ 55세\n“숨을 잘 못 쉬겠어요n\n0\n2주전\nL\nD\n하루 중 변화 없음\nCo\n집에 있으면 숨이 차는게 심해짐\n가만히 있으면 괜찮으나 계단을 걷거나 운동을 할 시 숨이 차다고 하심\nEx\n1년 전 여름에도 비슷한 증상\nC\n통증 없이 숨쉬기가 불편한 정도\nA\n[전신] 발열/부종/체중 변화/어지럼/출혈 경향( - / - / - / - / - )\n[호흡기] 오한/ 인후통/ 기침/가래/쌕쌕거림 (-/-/+ /-/->\n[순환기] 흉통/야간호흡곤란/두근거림( - / _ / - )\n[내분비] 더위불내성/설사( - / - )\n[정신 - 신경] 예기불안/공포/팔다리 근력 약화/공포감( - / - / ᅳ/ -)\nF\n숨쉬기를 악화시키는 요인 : 운동 시 심해짐, 여름에 더 심해짐\nE\n외\n과\n특이 사항 없음\n약\n특이 사항 없음\n人^\n중학교 선생님, 술(+, 1 〜2회/주, 소주 한 병)，담배(-)\n가\n특이 사항 없음\nGeneral\n특이사항 없음\nP/E\nHEENT\n빈혈(-), 부비동 압통(ᅳ), 경부 림프절 압통(ᅳ), 갑상샘(ᅳ)\n경정맥 (一)\nChest\n흉부 시/촉/ 타/청( - / - / —/-), 심장 청진(-)\nAbdomen\n간비대 (-)\nExtermity\n곤봉지/ 청색증/오목 부종(ᅳ/■/-)\n질문\n특이\n항\n\nCPX 주제별 내용 정리\nP |L\n/|s /V W \\\n|\nI 향\n신장/비뇨\n소변링: 변화\n(다뇨증/ 핍뇨)\n붉은색소변\n배뇨이상/소변찔끔증",
    "raw_profile_text": "성별/나이\n여성/ 52세\n\"숨이 차요”\n0\n오전 6시(현재 오전 10시)\nL\n-\nD\n지속\nCo\n비슷함\nEx\n처음\nC\n집안일 하기도 어려울 정도 말하는 것도 힘들어 보임, 화장실 가는 정도만 걸어도 숨\n이 참，가만히 있어도 숨이 참, 이전에는 계단을 올라도 숨이 차지 않았음\nA\n[전신] 발열/피로/체중 변화/부종(-/-/-/+，왼쪽 발목)\n[호홉] 흉통(+, 초반에 동반, 지속 시간 모름, 아프진 않고 답답한 느낌, NRS 3점)\n기침/가래/쌕쌕거림 ( - / - / - )\n[정신] 죽을것 같은 공포감(ᅳ). 불안( ± ,큰병일까봐)\nF\n운동 시 악화, 누우면 악화, 호흡 중등도 grade 4\n자세 상관 X, 찬 바람을 맞아본 적 없어서 악화되는지 잘 모르겠음\nE\n-\n외\n일주일 전 발목 골절되어 누워 지냄, 수술하거나 입원하지는 않음\n과\n관절염\n약\n관절영양제(먹다 안 먹다 한다고 강조함)\n사\n흡연(一), 음주(+, social)\n운동 ：\n관절 때문에 살 빼려고 운동 시작했으나 빗길에 넘어져 발목을 다친 뒤로 운동\n을 못하고 있음\n가\n-\n여\n폐경, 자녀 2명 자연분만\nGeneral\nV/S : 맥박 : 100회/분, 호흡 : 23회/분\nHEENT\n눈/구강(一/ - ), 갑상샘/ 림프절(ᅳ/-), 피부 긴장도/부종(ᅳ/一)\nP/E\nChest\n흉부 ：\n시/촉/타/청 (- / - / - / _ > . 심음 (_)\nExtermity\n곤봉지/청색증(-/-> , Homan’s sign : 하려했으나 반대편은 할 수\n있지만. 아픈 부위를 시도하면 부목 푼지 얼마되지 않았고, 아파서\n못하겠다고 거절, 왼쪽 발목에 멍 분장되어 있음, 실기 보는 날짜에\n따라 Homan’s sign 시행 가능 여부 다름(왼쪽 +, 오른쪽- )\n|oh\nm\nM\n질문\nI 이사항\n“갑자기 이렇게 심해서 큰 병은 아닐까 걱정돼요，아까 말씀하신 검사 결과는 언제 알 수\n있나요?二\n말이 느리고, 발목에 분장되어 있음\n\n실전\n모의\n증례 i\n' 54세 남자 임동재씨가 숨이 차서 응급실로 내원하였다.\n[활력 징후] 혈압 : 127/77mmHg\n맥박 : 85회/분\n상황\n호흡: 19희/분\n지침\n체온 ：\n36.5°C\n[응人I자는 이 환자에게] 증상과 관련된 병력을 청취하고\n증상과 관련된 적절한 신체 진찰을 시행한 후,\n추정 진단과 향후 진단 계획 등에 대해 환자와 논의하시오■\n환자\n교육\n• 가능성이 높은 진단 2개\n1. COPD\n2. 진폐증\n• 필요한 검사 계획 3가지\n1. 폐7 ᅵ능검사\n2. 흉부영상검사\n3. ABGA\n• 필요한 치료 계획 3가지\n1• 생활 습관 교육(e.g. 금연)\n2. 7 1관지확장제(LAM/V LABA)\n3. 응급 상황 교육\n환자가 호흡곤란증상으로 내원하면 그 원인이 호흡기인지 심혈관^인\n지 아니면 그 외의 원인인지 감별하는 것이 중요합니다. 호흡기에 의한\n호흡곤란의 경우환기장애, 가스교환장애, 호흡조절이상등이 원인이 될 수 있습니다. 본 증례의\n환자는 중년의 남자로 현재는금연 중이지만，과거 50갑년의 흡연자로 만성 폐쇄성폐질환{COPD)\n에 의한환기장애로 인한호흡곤•란이 가장의심됩니다. 환자는URIHx•가 있는데, COPD의 경우\nURI에 의한급성 악화가가능하기 때문에 만성 폐쇄성폐질환을 더욱 의심할수 있습니다. 그러나\n환자의 근무 환경 상 먼지가 많기 때문에 직업성 폐질환 역시 감별할 필요가 있습니다.\nCOPD의 경우 폐기능검사를통해 obstructive pattern 확인 및 BDRresponse로 기도의 비가역성\n을 확인하면 진단할 수 있습니다. 또한, CXR, HRCT 등을 통해 폐의 병 변을 확인할 수 있는데, 특히\n본증례의 환자는건강검진 상폐기종이 있으므로 CT •등어!서 해당 병변을관찰할수 있습니다.\n\n성별/나이\n남성/ 54세\n주소\n“숨이 차요(환자가 침대에 앉아 있음)”\n0\n6개월 전\nL\n-\nD\n지속\nCo\n과거에 감기 걸렸을 때 기침, 가래 심하고 숨이 찼는데, 그때 감기에서 회복하고 괜찮\n았다가 6개월 전부터 호흡곤란 다시 생김\nEx\n감기 걸린 뒤로 호흡곤란 증상 다시 생긴 것 같음\nC\n가만히 있을 때는 괜찮음，옷 갈아입을 때는 괜찮음, 일하거나 계단 오를 때 숨 차는\n증상 심함，평지 걸어도 동년배에 비해 뒤처짐(-)\n무거운 것 들 때(+)\nA\n[전신] 발열/오한/피로/체중 변화/부종( - / - / - / - / - )\n[호흡] 흉통/두근거림/인후통/쌕쌕거림(ᅵ/■/+，6개월 전 감기 때/ - )\n기침/가래/콧물(ᅳ/+, 흰색，아침에 회색으로 나오고 시간 지나면 맑아짐，\n\n하루 양 합치면 티스푼 1 개 정도/一), “가래 억지로 뱉으려고 기침 많이 함”\n[정신] 죽을것 같은공포감(一),불안(ᅵ)\n입술 부종/두드러기( - / - )\nF\n운동 및 움직이면 악화, 쉬면 완화\nE\n8년 전, 4년 전 둘 다 폐기종(+), \"폐가 커져 있다고 들었어요”\n독감. 폐렴구균 예방접종은 맞았다고 말함\n외\n-\n과\n-\n약\n-\n人卜\n음주( - ) ，흡연(+, 2PX25Y+10년 전 끊음)\n직업 : 정육식당 운영 ( 먼지는 없는데 연기가 많음)，일할 때 호흡곤란 더 심해짐 (+)\n가\n-\nP/E\nGeneral\nV/S ：\nstable\nHEENT\n눈/구강(一/ - ), 갑상샘/ 림프절(-/-> ，피부 긴장도/부종( - / - )\nChest\n흉부 시/촉/ 타/청( - / - / - / - ) , 심음(-)\nExtermity\n곤봉지/청색증(一/ᅳ)\n질문\n-\n특이사항\n-\n\nw m i 실전모의증례\n• 43세 남자 신정호씨가 숨이 차 내원하였다.\n^•황\n지침\n[활력 징후] 혈압 : 114/70mrmHg\n맥박 : 80회/분\n호흡 : 18회/분\n체온 : 37.213\n[응시자는 이 환자에게]\n증상과 관련된 병력을 청취하고\n증상과 관련된 적절한 신체 진찰을 시행한 후,\n추정 진단과 향후 진단 계획 등에 대해 환자와 논의하시오\n• 가능성이 높은 진단 3개\n1. 만성 폐쇄성폐질환\n2. 간질성 폐질환\n3. 폐암\n• 필요한 검사 계획 3가지\n교육\n1. 폐7 ᅵ능검사\n2. 흉부 X-ray\n3. 흉부 CT\n• 필요한 치료 계획 2가지\n1. 기관지확장제\n2. 금연\n환자는 2년 전부터 호흡곤란을 호소하고 있었으며, 흡연력도 25갑년\n으로 가래, 쌕쌕거림으로 만성 폐쇄성폐질환이 가장 의심되는 상황입\n니다• 평소 약물 사용이 중요함을 교육하고, 급성 악화 시 처치 방법에 대해서 반드시 교육하여\n야합니다.\n호흡곤란으로 불안을 호소하거나 숨이 차 대답하는데 어려음이 있을 수 있으니, 이를 배려하여\n문진하는 것이 좋겠습니다. 만성 폐쇄성폐질환 환자는 호흡기 질환 고위험군으로 예방접종 여\n부도 확인하고 교육 시에 고려해야 합니다.\n----------------------- ----------------------------------------------------------------- ----------------------------\n\n성별/나이\n남성/ 43세\n주소\n“숨이 차요”\n0\n3개월 전\nL\n-\nD\n-\nCo\n3개월 전부터 더 심해짐\nEx\n2년 전부터\nC\n2년 전에는 계단 오를 때 힘듬. 최근엔 평지 걸어도 숨 참\n평범한 일상 생활이나 휴식 시에는 괜찮음\nA\n[전신]\n발열/식은땀/체중감소/오한/피로감 ( - / - / _ / - / - )\n[호홉기/ 순환기]\n기침/콧물/ 가래/두근거림\n(- / - / + , 1 달 전부터. 노란색이었다가 요즘 흰색으로 바뀜/一)\n쌕쌕거림(+), 가슴 통증/야간 발한/객혈/흉통(- / - / - / 니\n[내분비]\n더위불내성(ᅳ)\n[정신]\n불안/죽을 것 같은 느낌(一/ᅳ)\nF\n악화 : 운동 시(+), 누운 자세/찬 공기/일중 변화/계절 변화( - / - / - / - )\n완화 : 휴식 (+>\nE\n1 년 전 건강 검진 상 이상 없음, 당시 흉부 X-ray 찍음\n외\n최근 오래 누워 있었던 적(ᅳ)\n과\n1 년 전 심한 감기, 천식/결핵/아토피 피부염/알러지 비염(一/ - / - / ᅳ)\n약\n-\n人^\n술(+. social), 담배(+, 25갑년. 하루 1갑)\n직업 : 택배 기사(먼지 많지 않음)/운동(ᅳ)\n가\n-\nP/E\nGeneral\nV/S 확인\nHEENT\n결막/공막( - / - ) , 입/피부 탈수 소견(一/ - ), 림프절(-)\nChest\n흉부 시/촉/타/청( - / - / - / - ) . 심장 청진(-)\nExtermity\n피부 긴장도，오목 부종 정상. 곤봉지(- )\n질문\n“택배 일에 지장이 갈까 걱정이에요.”\n특이 사항\n대답이 느려서 시간이 부족할 수 있음\n\nn { 실전\n모의\n증례\n• 34세 남자 박현우씨가 숨 쉬는 게 힘들어 내원하였다.\n지침\n[활력 징후] 혈압 : 110/82mmHg\n맥박 : 74회/분\n^흡 : 23회/분\n체온 ：\n37.2°C\n[응시자는 이 환자에게] 증상과 관련된 병력을 청취하고\n증상과 관련된 적절한 신체 진찰을 시행한 후,\n추정 진단과 향후 진단 계획 등에 대해 환자와 논의하시오■\n• 가능성이 높은 진단 3개\n1. 급성 심부전\n2. 급성 바이러스 폐렴\n3. 심장막염\n환자\n• 필요한 검사 계획 3가지\n1. 심초음파\n2. 흉부 X-ray\n3. 혈액검人卜\n• 필요한 치료 계획 1 가지\n1. 익물 치료\n호소하는 증상이 애매하여 확실히 진단이 좁혀지지 않는 증례입니다.\n처음 CPX를 시작할 때는 추정 진단에 대해서 확신이 없으면 환자에게\n말을 꺼낼 때 조심스러워하는 경향이 있습니다. 내가 생각한 것이 맞을까 걱정하는 것이지요.\nCPX에서 중요한 것은 실제적 인 답이 아니라, 얼마나 논리적으로 추정 진단을 잡았고 그를 자신\n있게 말할 수 있냐는 것입니다. 병력 청취만으로 추정 진단이 확실하게 좁혀지지 않더라도 자신\n있계 추정 진단과그에 따른 검사를 설명할 수 있도록 연습하세요.\n현재 환자의 경우 심부전이 가장 의심되고, 단서가 조금부족하긴 하나 최근 감염으로 인해 심\n근에 감염이 생기고, 그로 인해 심부전이 생기지 않았을까추정해 볼 수 있습니다.\n\n성별/나이\n남성/ 34세\n“숨 쉬는 게 힘들어요”\n0\n3일 전\nL\n-\nD\n3일 내내 지속됨\nCo\n심해짐\nEx\n-\nC\n평소에도 계단 올라갈 때 숨이 참, 3일 전부터 평지 걸어도 숨 참\n휴식할 때 괜찮음\nA\n[전신] 발열(+, 최근 감기 걸렸을 때 발열), 식은땀/체중 감소/오한(一/ᅳ/ᅳ)\n피로감(+), 최근 감기(+, 일주일 전)\n[호흡기/순환기]\n기침/콧물/가래/두근거림 (+, 누울 때 악화/ - / 一/ᅳ)\n쌕쌕거림/가슴 통증/야간 발한/객혈/흉통(一/一/一/ - / - )\n부종(+, 얼굴)\n[내분비]\n더위불내성(一)\n[정신]\n불안卜),죽을것 같은 느낌(ᅳ)\nF\n악화 : 움직일 때(+), 누운 자세(+)\nE\n건강 검진에서 이상 없음\n외\n최근 오래 누워 있었던 적(ᅳ)\n과\n고지혈증(+, 치료 받지 않음), 천식(+, 어렸을 때)\n결핵/아토피 피부염/알러지 비염(ᅳ/ - / - )\n약\n감기약(+, 최근 감기로 4일 전 복용, 현재 중단)\n人^\n술(+. 일주일에 1 〜2번, 하루에 소주 3잔), 담배(+, 17갑년，하루 1 갑)\n직업 : 마트 배송 업무( 먼지 많지 않음)\n가\n-\nP/E\nGeneral\nV/S 확인\nHEENT\n결막/공막(-/ -), 입/피부 탈수 소견(-/->, 림프절/목정맥 확장(- / - )\nChest\n흉부 시/촉/타/청(ᅳ/_/-/_> , 심장 청진(ᅳ)\nExtermity\n피부 긴장도* 오목 부종 정상, 곤봉지(-)\nId*\nn|oi<\n신\n:\n질문\n\nB\n[ 실전\n모의\n증례\n• 26세 여자 신지은씨가 숨이 차 힘들어 내원하였다.\n^■황\n지침\n[활력 징후] 혈압 : 114/78mmHg\n맥박 : 80회/분\n호흡 : 17회/분\n체온 : 37.5°C\n[응人I자는 이 환자에게]\n증상과 관련된 병력을 청취하고\n증상과 관련된 적절한 신체 진찰을 시행한 후,\n추정 진단과 향후 진단 계획 등에 대해 환자와 논의하시오\n• 가능성이 높은 진단 2개\n1. 결핵\n2. 기흉\n• 필요한 검사 계획 3가지\n교육\n1. 흉부 X-ray\n2. 객담항산균검사\n3. 흉부 CT\n• 필요한 치료 계획 1 가지\n1. 항결핵제\n호흡곤란은 다양한 계통의 문제로 생길 수 있습니다.\n콜\n'\n이 환자의 경우 명확히 결핵이라고 진단 내릴 순 없지만 어머니의 결\n핵 과거력, 야간 발한，기침 등으로 결핵이 가장 의심되는상황입니다.\n결핵의 경우 꾸준한 치료가 중요함을 설명하고, 동거인도 같이 검사를 받아야 된다는 점, 일정\n기간 격리가 필요함을 설명해야겠지요.\n\n성별/나이\n여성/ 26세\n“가슴이 답답해요”\n0\n1주전\nL\n-\nD\n-\nCo\n-\nEx\n-\nC\n운동, 계단 오를 때 숨 참，휴식 시나 평지 걸을 때는 괜찮다.\nA\n[전신]\n발열/식은땀/체중 감소/오한/피로감/최근 감기\n(+，최근에 밤에 열이 조금 나는 것 같기도 함/ - / - / + /+ /-)\n[호흡기/ 순환기]\n기침/콧물/가래/두근거림 (+/ᅳ/一/ - )\n쌕쌕거림/가슴 통증/야간 발한/객혈/부종( - / _ / + / - / _ )\n오른쪽 등 뻐근한 느낌, 가슴 답답함(+, 1달 전부터)\n[내분비]\n더위불내성(一)\n[정신]\n불안/죽을 것 같은 느낌(ᅳ/ᅳ)\nF\n악화 : 움직일 때(+), 완화 : 휴식(+)\n숨쉴 때 가슴통증심해짐\nE\n-\n외\n최근 오래 누워 있었던 적(ᅳ)\n과\n천식/결핵/아토피 피부염/알러지 비염( - / - / - / - )\n약\n-\n사\n술/담배(一/一), 직업 : 운동 관련 자격증 준비 중\n가\n1\n어머니 : 결핵(20년 전)，부모님과 함께 거주 중/동생 ：\n알레르기성 천식\n여\n규칙적\nP/E\nGeneral\nV/S 확인\nHEENT\n결막/공막(一/ - )，입/피부 탈수 소견(- / - ), 림프절/목정맥 확장(一/-)\nChest\n흉부 시/촉/ 타/청( - / - / - / 一), 심장 청진(-)\nExtermity\n피부 긴장도，오목 부종 정상. 곤봉지(- )\n질문\n“치료 중에는 운동해도 되나요? ”\n특이職\n-\nS\n\n느\n\n■\n실전\n모의\n증례\n• 58세 여자 황윤정씨가 숨이 차서 내원하였다.\n[활력 징후] 혈압 : 120/80mmHg\n맥박 : 80회/분\n호音 : 16호|/분\n지침\n체온 ：\n36.81C\n|轉義|옳馨\n[응시자는 이 환자에게] 증상과 관련된 병력을 청취하고\n증상과 관련된 적절한 신체 진찰을 시행한 후.\n추정 진단과 향후 진단 계획 등에 대해 환자와 논의하시오\nV스f 시 震■'重• 가능성이 높은 진단 3개\n환자\n1. COPD\n2. IPF\n3. 심부전\n교육\n• 필요한 검사 계획 3가지\n1. 흉부 X-ray\n2. 폐71능검사\n3. 흉부 CT\n호흡곤란은 갑자기 발생한 것인지 꾸준히 악화된 것인지를 구분하는\n것이 먼저 해야할 일입니다. 갑자기 발생한 것이라면 응급상황일 수\n있으므로 빠르게 처치하고, 검사와 치료를 속히 진행해야합니다.\n이 케이스의 경우 만성적인 호흡곤란이므로 COPD, IPF, 천식, 심부전 둥을 염두해 두고 접근하\n는 것이 적절합니다.\n진폐증의 경우 직업력이 중요하므로 어떠한 일을 하는지 확인하는 것도 중요합니다.\n\n성별/나이\n여성/ 58세\n^소\n“일할 때 숨 차요”\n0\n3개월 전\nL\n-\nD\n-\nCo\n심해짐\nEx\n3년 전. 계단오를 때 숨참\nC\n흰색 가래 동반, 객혈(-)\nA\n[전신]\n발열/식은땀/체중감소/오한/피로감 ( - / - / - / - / - )\n[호흡기/ 순환기]\n호흡곤란/흉통/어지럼/두근거림 (+/- / 一/ - )\n기침/가래/쌕색거림 (+/+/+)\n[정신]\n우울/불안 (-/->\nF\n악화 : 운동할 때\n완화 : 휴식/자세에 따른 변화 없음\nE\n외\n과\nDM/TB/HTN/간염 ( - / - / - / - )\n약\n-\n사\n술(+, social), 담배(+, 25갑년)\n직업 ：\n인테리어 업자，Stress(-)\n가\n여\n폐경\nP/E\nGeneral\nV/S 확인\nHEENT\n구강 탈수 소견(ᅳ), 갑상샘(ᅳ)\nChest\n흉부 시/청/타/촉 정상, 심음(-)\nExtermity\n피부 긴장도/오목 부종( - / - )\n곤봉지 (-)\n질문\n특이 사항\n대답이 느려서 시간이 부족할 수 있음\n\na { 실전\n모의\n증례\n• 65세 여자 김지민씨가 숨쉬기가 힘들어 내원하였다.\n지침\n馨나 ■\nV.；\n•\n[활력 징휘 혈압 : 130/85mmHg\n맥박 ：\n102회/분\n■2■音 : 28회/분\n체온 : 36.6°C\n[응시자는 이 환자에게] 증상과 관련된 병력을 청취하고\n증상과 관련된 적절한 신체 진찰을 시행한 후,\n추정 진단과 향후 진단 계획 등에 대해 환자와 논의하시오•\n• 가능성이 높은 진단 2개\n환자\n1.PTE\n2. DVT\n교육\n• 필요한 검사 계획 3가지\n1. ABGA\n2. Chest CT\n3. 다리정맥초음파\n예상\n1. 설명동의서 받기 : 흉부 조영 CT 검사가 필요한 환자이므로 검사에 대해 설명하\n고 동의서를 받습니다.\n술기\n2. 환자 상태 보고 ：\n응급실에 내원한 환자의 시나리오로 교수님께 환자 상태 보고를\n시행할 수 있습니다.\ny ^ x\n호흡곤란의 원인을 호흡기, 순환기，내분비, 정신으로 나누어 잘 정리\n해두도록합니다.\n갑자기 호흡곤란이 심해지는 경우 응급 상황일 수 있으므로 바로 병원으로 오도록 잘 교육하고>\n원인을 감별하기 위해서 위 케이스 경우 이전 수술/외상 여부를 꼭 확인하도록 합니다.\n원인을 감별하기 위해서 호흡 양상，흡연력, 악화 요인 등을 잘물어 보도록 합니다.\n\n성별/나이\n여성/ 65세\n주소\n“숨쉬기가 너무 힘들어요”\n0\n2시간 전\nL\n가슴전체\nD\n계속\nCo\n처음과 비슷\nEx\nC\n가슴 전체의 답답함과 뻐근함 호소\nA\n[전신]\n발열/오한/식은땀/체중 감소( - / - / - / - )\n[호흡기/순환기]\n호흡곤란/흉통 (+ /-)\nF\n악화 (+) : 누울 때\nE\n-\n외\n다리 골절 (+) : 2주간 누워 있음\n과\nD M /T B /H T N /간염 ( - / - / + / - )\n약\nAmlodipine(혈압 잘 조절됨), 폐경 치료(-)\n사\n술/담배/커피 ( - / - / - )\n가\n언니 : 고혈압, 아버지 : 심근경색으로 人방\n여\n폐경\nGeneral\nV /S 확인\nHEENT\n입/피부 탈수 소견( - / - ) , 결막/공막( - / - )\nP/E\nChest\n-\nAbdomen\n-\nExtermity\nRt. Homan sign(+)\nQ|0I>\nvj\n질문\n특이 ^卜항\n신체 진찰하는 침대에 앉아 있음\n\na { 실전\n모의\n증례\n• 70세 남자 박진영씨가 숨이 차서 내원하였다.\n[활력 징후] 혈압 : 120/80mmHg\n맥박 : 90회/분\n^■황\n오읍 - 18회/분\n지침\n체온 ：\n36.6°C\n[응시자는 이 환자에게] 증상과 관련된 병력을 청취하고\n증상과 관련된 적절한 신체 진찰을 시행한 후,\n추정 진단과 향후 진단 계획 등에 대해 환자와 논의하시오.\n삶’\n• 가능성이 높은 진단 3개\n환자\n1. COPD\n2. 천식\n3. 특발성 폐섬유화증\n7■교육\n• 필요한 검사 계획 3가지\n1. 폐고 I능검人F\n2. 단순 흉부 방사선 촬영\n3. 흉부 CT\n호흡곤란의 원인을 호흡기，순환기, 내분비, 정신으로 나누어 잘 정리\n해 두도록 합니다. 갑자기 호흡곤란이 심해지는 경우응급 상황일 수\n있으므로 바로 병원으로 오도록 잘 교육하고，원인을 감별하기 위해서 호흡 양상, 홉연력, 악화 요\n인 등을 잘 물어 보도록 합니 다.\n위의 케이스 경우금연과 독감 예방접종의 중요성에 대해서 잘 설명하도록 합니다.\n\nᅵ\n‘ᅵ\n」—■\n^ —\n성별/나이\n남성/ 70세\n“숨쉬기가 너무 힘들어요”\n0\n1년전\nL\n-\nD\n^卜루 종일\nCo\n심해짐\nEx\n-\nC\n들이쉴 때, 내쉴 때 차이 없음\nA\n[전신] 발열/오한/부종/체중 변화( - / ᅳ/ - / - )\n[호흡기/ 순환기] 기침/콧물/가래/두근거림(ᅳ/ᅳ/ᅳ/ᅳ), 쌕쌕거림(+)\n[소화기] 설사/구토( - / - )\n[내분비] 더위불내성 (-)\nF\n악화 (+) ：\n운동 후, 일상 생활 지장은 심하지 않음\nE\n-\n외\n과\nDM/TB/HTN/간염 (- / - / + / - )\n약\n혈압약 (+)\n사\n술(-, 끊은 지 20년)，담배(+. 50갑년), 커피 (-)\n가\n어머니 : 고혈압\nGeneral\nV/S 확인\nP/E\nHEENT\n입/피부 탈수 소견( - / 一)，결막/공막(ᅳ/ - )\n경동맥/경정맥 정상\n■샘 정상\nChest\n심음 정상\n숨 크게 들이쉬지 못함\nAbdomen\n-\nExtermity\n-\n질문\n특이\n항\n-\n\nEM\n\n실전모의증례\n•\n• 47세 남자 김재환씨가 숨을 쉬기 어렵다며 내원하였다.\n[활력 징후] 혈압 : 124/68mmHg\n맥박 : 90회/분\n^■황\n호흡 : 18회/분\n지침\n체온 ：\n36.4°C\n[응시자는 이 환자에게] 증상과 관련된 병력을 청취하고\n증상과 관련된 적절한 신체 진찰을 시행한 후,\n추정 진단과 향후 진단 계획 등에 대해 환자와 논의하시오.\n• 가능성이 높은 진단 3개\n1. 진폐증\n2. COPD\n3. 폐결핵\n• 필요한 검사 계획 2가지\n1.CXR\n2.ABGA\n댜\n호흡곤란은 응급일 수 있는케이스입니다. 따라서 진료 시작 전, 진료\n받기 너무 힘드制는 않은지 여쯤고，진료 도중에라도 언제든 힘드시\n면 말씀해 달라고 한 뒤 진료를 시작하시 면 좋습니다.\n건강 검진 꼭 여줘보시고, 직업력의 경우에는 가끔 탄광일 하시거나 먼지 많은곳에서 일한 적\n없으신 지 콕 찝어서 여줘봐야 상세히 알려주시는 경우도 있습니다.\n흉부 신체 진찰 때에는 꼭 환자분께 상의를 위로 을려도 되는지 여줍고> ‘맨살’ 위에 진찰하셔야\n하는 것 잊지 않으셔야 합니다.\n실제로 연습 때 항상 옷 위로 진찰하다가 시험장에서도 똑같이 옷 위로 P/E한 분들 꽤 있었다는\n사실을 기억하기 바랍니다.\n\n성별/나이\n남성/ 47세\n.\n.\n“숨이 차요”\n0\n3달 전\nL\n-\nD\n지속적\nCo\n비슷함\nEx\n처음\nC\n주로 운동하거나 계단 오를 때 숨차고 휴식 시 완화\nA\n[전신] 발열(- )，체중 변화( - )，실신(-)\n[호흡기] 기침(+, 6달 전부터), 가래(-), 흉통(一). 쌕쌕거림(一)\n[출혈 경향] 양치할 때 피가 잘 나는지(ᅳ)\n[정신] 스트레스(- ), 불안( - ) ,공황장애(-)\n[기타] 다리 부종/압통/발적(一/一/ - )\nF\n[악화] 계단 오를때,운동할때\n[완화] 휴식/자세，계절, 시간,장소에는 무관함\nE\n5년 전 건강 검진 : CXR 상 뿌연 폐\n외\n과\nDM/HTN/dyslipidemia/TB/^g(-/-/-/+/-) ：\n대학생 때 결핵 앓은 후 완치\n약\n卜특이사항^음\n人^\n술 : 가끔，담배 : 5년 전 끊음(과거 35갑년)\n직업 : 현재 철물점(5년), 과거 탄광(15년), 공人f장(15년) 일했음\n가\n어머니 : 폐렴，아버지 : 고혈압\nGeneral\n활력 징후 확인 ：\n혈압, 맥박수. 호흡수 확인 후 응급 상황 배제\nP/E\nHEENT\n눈(결막) 시진 경정맥 시진, 경동맥 청진, 경부 갑상샘. 림프절 촉진\n정상\nChest\n흉부 시/촉/타/청, 심장 청진 모두 정상\nAbdomen\n-\nExtermity\n곤봉지, 청색증 모두 정상\n질문\n-\n특이 人땅\n-\n\n1^\n\n실전\n모의\n증례\n지침\n• 55세 남자 이규범씨가 숨을 쉬기 어렵다며 내원하였다.\n[활력 징후] 혈압 : 120/80mmHg\n맥박 ：\n81회/분\n호흡 : 21회/분\n체온 ：\n36.8°C\n[응시자는 이 환자에게] 증상과 관련된 병력을 청취하고\n증상과 관련된 적절한 신체 진찰을 시행한 후.\n추정 진단과 향후 진단 계획 등에 대해 환자와 논의하시오\n환자\n교육\n• 가능성이 높은 진단 3개\n1. 천식\n1. 알레르기 비염\n3. 기관지 천식\n• 필요한 검사 계획 3가지\n1. 폐7 1능검사\n2. 피부따끔검사\n3. 7 1관지내시경\n계절에 호흡곤란이 심해지는 환자입니다. 또한 운동 시에도 심해지고\n이전에도 비슷한 경험이 있던 환자입니다. 신체 진찰에서 이상 소견이\n없었던 점을 모두 고려했을 때 천식이 가장 의심됩니다. 하지만 그 외에도 호흡곤란에는 여러\n원인이 있기 때문에 의심가는 질환만 물어 볼 것이 아니라 다양한 원인 감별을 위한 질문을 해\n야할 것입니다.\n천식같은 경•우는 교육이 중요하기 때문에 교육도 꼼꼼히 해야 할 것입니다.\n-------------------\n^\n\n성별/나이\n남성/ 55세\n“숨을 잘 못 쉬겠어요n\n0\n2주전\nL\nD\n하루 중 변화 없음\nCo\n집에 있으면 숨이 차는게 심해짐\n가만히 있으면 괜찮으나 계단을 걷거나 운동을 할 시 숨이 차다고 하심\nEx\n1년 전 여름에도 비슷한 증상\nC\n통증 없이 숨쉬기가 불편한 정도\nA\n[전신] 발열/부종/체중 변화/어지럼/출혈 경향( - / - / - / - / - )\n[호흡기] 오한/ 인후통/ 기침/가래/쌕쌕거림 (-/-/+ /-/->\n[순환기] 흉통/야간호흡곤란/두근거림( - / _ / - )\n[내분비] 더위불내성/설사( - / - )\n[정신 - 신경] 예기불안/공포/팔다리 근력 약화/공포감( - / - / ᅳ/ -)\nF\n숨쉬기를 악화시키는 요인 : 운동 시 심해짐, 여름에 더 심해짐\nE\n외\n과\n특이 사항 없음\n약\n특이 사항 없음\n人^\n중학교 선생님, 술(+, 1 〜2회/주, 소주 한 병)，담배(-)\n가\n특이 사항 없음\nGeneral\n특이사항 없음\nP/E\nHEENT\n빈혈(-), 부비동 압통(ᅳ), 경부 림프절 압통(ᅳ), 갑상샘(ᅳ)\n경정맥 (一)\nChest\n흉부 시/촉/ 타/청( - / - / —/-), 심장 청진(-)\nAbdomen\n간비대 (-)\nExtermity\n곤봉지/ 청색증/오목 부종(ᅳ/■/-)\n질문\n특이\n항\n-\n\nCPX 주제별 내용 정리\nP |L\n/|s /V W \\\n|\nI 향\n신장/비뇨\n소변링: 변화\n(다뇨증/ 핍뇨)\n붉은색소변\n배뇨이상/소변찔끔증"
  },
  "examiner_only": {
    "scenario_task": "증상과 관련된 병력을 청취하고\n증상과 관련된 적절한 신체 진찰을 시행한 후,\n추정 진단과 향후 진단 계획 등에 대해 환자와 논의하시오\n교육",
    "likely_diagnoses": [
      "폐색전증"
    ],
    "planned_tests": [
      "흉부영상검人KCT)",
      "듀얼 도플러초음파",
      "ABGA, 심전도"
    ],
    "planned_treatments_or_education": [
      "입원 권유",
      "약물 치료"
    ],
    "expected_skills_raw": null,
    "author_commentary_tail": null,
    "scenario_card_raw": "■ 16\n호흡곤란 (Dyspnea)\n호흡기\nD\ni 실전 모의 증례 S\n지침\n• 52세 여자 강민경씨가 숨이 차서 응급실로 내원하였다.\n[활력 징후] 혈압 : 125/80mmHg\n맥박 ：\n100회/분\n^흡 : 23회/분\n체온 ：\n36.5°C\n[응시자는 이 환자에게] 증상과 관련된 병력을 청취하고\n증상과 관련된 적절한 신체 진찰을 시행한 후,\n추정 진단과 향후 진단 계획 등에 대해 환자와 논의하시오-\n교육\n•가능성이 높은 진단 1개\n1. 폐색전증\n• 필요한 검사 계획 3가지\n1. 흉부영상검人KCT)\n2. 듀얼 도플러초음파\n3. ABGA, 심전도\n• 필요한 치료 계획 2가지\n1. 입원 권유\n2. 약물 치료\n갑자기 발생한 호흡곤란 때문에 응급실로 내원한 환자입니다. 호흡곤\n란의 경우 환자가 매우 불안해하고 불편감을 호소하기 때문에 빠른 문\n진 후 적절한 조치를 취하는 것이 중요합니다. 원인에 따라 치명적인 결과를 초래할수 있기 때\n문에 신속한 원인 감별이 무엇보다 중요합니다.\n본 환자의 경우 일주일 전 발목 골절로 누워서 지냈다는 과거력을 통해 PTE(PE ；\n폐색전증)를\n의심할수 있고, 왼발의 부종과발적, Homans sign 양성 소견올 통해 이를 더욱 확신할 수 있습\n니다. 특히 Homan’s sign 양성은 DVT에 의한 폐색전증으로 급성 호흡곤란이 발생했을 가능성\n을나타1i 니다. 따라서 정확한원인 파악을위해 조영 증강흥부C T 검사와하지의 혈전 확인을\n위한 듀얼 도플러초음파 검사를 해 볼 수 있습니다.\n본 환자의 경우 V/S이 stable하므로 secondary prevention을 위한 anticoagulation therapy를\n시도해 블 수 있고> 경우에 따라 IVC filter를 거치할 수 있습니다."
  },
  "simulation_policy": {
    "answer_scope": "Respond only with facts in patient_visible. Do not disclose examiner_only content.",
    "disclosure_behavior": [
      "Do not volunteer all symptoms, history, or examination information at once.",
      "Reveal a fact only when the student's question or requested examination reasonably targets that fact.",
      "Use natural patient language rather than medical diagnosis names.",
      "Do not invent values, events, history, diagnoses, or test results that are absent from this case.",
      "If a requested fact is not present in the case, answer with an uncertainty-safe response such as '그 부분은 잘 모르겠어요' rather than fabricating details.",
      "If the student asks for an examination, report only the corresponding documented finding from physical_exam_results."
    ]
  },
  "quality": {
    "flags": [],
    "requires_manual_review": false
  }
}